coblack/__init__.py
coblack/format_file.py
comform/__init__.py
comform/format_file.py
coblack-0.2.dist-info/LICENSE
coblack-0.2.dist-info/METADATA
coblack-0.2.dist-info/WHEEL
coblack-0.2.dist-info/entry_points.txt
coblack-0.2.dist-info/top_level.txt
coblack-0.2.dist-info/RECORD
