Metadata-Version: 2.1
Name: coblack
Version: 0.2
Summary: Black-compliant formatter/rewrapper for Python comments.
Home-page: https://github.com/tfiers/coblack
Author: Tomas Fiers
Author-email: tomas.fiers@gmail.com
License: UNKNOWN
Project-URL: Source Code, https://github.com/tfiers/coblack
Platform: UNKNOWN
Classifier: Intended Audience :: Developers
Classifier: Environment :: Console
Classifier: Operating System :: OS Independent
Classifier: Programming Language :: Python :: 3
Classifier: License :: OSI Approved :: MIT License
Requires-Python: >= 3.8
Requires-Dist: click (~=7.1)
Requires-Dist: black (>=20)
